trossen_slate-0.0.3.dist-info/RECORD
trossen_slate-0.0.3.dist-info/WHEEL
trossen_slate-0.0.3.dist-info/METADATA
trossen_slate/trossen_slate.cpython-311-aarch64-linux-gnu.so
trossen_slate/trossen_slate.pyi
trossen_slate/__init__.py
trossen_slate/__init__.pyi
trossen_slate.libs/libbz2-738ca772.so.1.0.6
trossen_slate.libs/liblzma-6bd50f17.so.5.2.2
trossen_slate.libs/libdw-0-46ed0dd9.176.so
trossen_slate.libs/libattr-aed5a3b1.so.1.1.0
trossen_slate.libs/libcap-47c73bce.so.2.22
trossen_slate.libs/libudev-5b0d4adc.so.1.6.2
trossen_slate.libs/libelf-0-ef69846b.176.so
lib/libtrossen_slate.a
